fybdthemes/__init__.py
fybdthemes/diverging.py
fybdthemes/plot.py
fybdthemes/qualitative.py
fybdthemes/sequential.py
fybdthemes/theme.py
fybdthemes-0.1.2.dist-info/METADATA
fybdthemes-0.1.2.dist-info/WHEEL
fybdthemes-0.1.2.dist-info/licenses/LICENSE
fybdthemes-0.1.2.dist-info/RECORD
