Metadata-Version: 2.1
Name: fybdthemes
Version: 0.1.2
Summary: Color palettes and plot themes
Project-URL: Homepage, https://github.com/dirmeier/fybdthemes
Author-email: Simon Dirmeier <sfyrbnd@pm.me>
License-Expression: Apache-2.0
License-File: LICENSE
Keywords: color palettes,themes
Classifier: Development Status :: 1 - Planning
Classifier: Intended Audience :: Science/Research
Classifier: License :: OSI Approved :: Apache Software License
Classifier: Programming Language :: Python :: 3
Classifier: Programming Language :: Python :: 3.10
Classifier: Programming Language :: Python :: 3.11
Classifier: Programming Language :: Python :: 3.12
Requires-Python: >=3.9
Requires-Dist: matplotlib>=3.3.3
Requires-Dist: numpy>=1.19.4
Requires-Dist: palettable>=3.3.3
Requires-Dist: seaborn>=0.11.0
